cms17hw/main.py
cms17hw/utils.py
csm17_hw-0.2.0.dist-info/METADATA
csm17_hw-0.2.0.dist-info/WHEEL
csm17_hw-0.2.0.dist-info/entry_points.txt
csm17_hw-0.2.0.dist-info/top_level.txt
csm17_hw-0.2.0.dist-info/RECORD
