Metadata-Version: 2.2
Name: CSM17_HW
Version: 0.2.0
Summary: CSM17 과제전형
Author-email: mingk42 <xoals123456t@gmail.com>
License: MIT
Project-URL: Github, https://github.com/Mingk42/csm17
Requires-Python: >=3.11
Requires-Dist: bs4>=0.0.2
